README.txt
setup.py
docs/HISTORY.txt
docs/INSTALL.txt
docs/LICENSE.GPL
docs/LICENSE.txt
xm/__init__.py
xm.portlets.egg-info/PKG-INFO
xm.portlets.egg-info/SOURCES.txt
xm.portlets.egg-info/dependency_links.txt
xm.portlets.egg-info/entry_points.txt
xm.portlets.egg-info/namespace_packages.txt
xm.portlets.egg-info/not-zip-safe
xm.portlets.egg-info/requires.txt
xm.portlets.egg-info/top_level.txt
xm/portlets/__init__.py
xm/portlets/configure.zcml
xm/portlets/iterations.pt
xm/portlets/iterations.py
xm/portlets/managers.pt
xm/portlets/managers.py
xm/portlets/project.pt
xm/portlets/project.py
xm/portlets/rebuild_i18n.sh
xm/portlets/version.txt
xm/portlets/locales/xm.portlets.pot
xm/portlets/locales/de/LC_MESSAGES/xm.portlets.po
xm/portlets/locales/nl/LC_MESSAGES/xm.portlets.po