Metadata-Version: 1.0
Name: xm.portlets
Version: 0.9
Summary: Portlets for XM
Home-page: http://svn.plone.org/svn/collective/xm.portlets
Author: Jean-Paul Ladage
Author-email: j.ladage@zestsoftware.nl
License: GPL
Keywords: xm portlets
Platform: UNKNOWN
Classifier: Framework :: Plone
Classifier: Framework :: Zope2
Classifier: Framework :: Zope3
Classifier: Programming Language :: Python
Classifier: Topic :: Software Development :: Libraries :: Python Modules
